MANIFEST.in
README.txt
setup.py
docs/.HISTORY.txt.un~
docs/HISTORY.txt
docs/INSTALL.txt
docs/LICENSE.GPL
docs/LICENSE.txt
docs/ROADMAP.txt
wc/__init__.py
wc.pageturner.egg-info/PKG-INFO
wc.pageturner.egg-info/SOURCES.txt
wc.pageturner.egg-info/dependency_links.txt
wc.pageturner.egg-info/entry_points.txt
wc.pageturner.egg-info/namespace_packages.txt
wc.pageturner.egg-info/not-zip-safe
wc.pageturner.egg-info/requires.txt
wc.pageturner.egg-info/top_level.txt
wc/pageturner/.pageturner.pt.un~
wc/pageturner/__init__.py
wc/pageturner/configure.zcml
wc/pageturner/convert.py
wc/pageturner/events.py
wc/pageturner/interfaces.py
wc/pageturner/migration.py
wc/pageturner/pageturner.pt
wc/pageturner/settings.py
wc/pageturner/setup.py
wc/pageturner/tests.py
wc/pageturner/version.txt
wc/pageturner/views.py
wc/pageturner/profiles/default/actions.xml
wc/pageturner/profiles/default/browserlayer.xml
wc/pageturner/profiles/default/controlpanel.xml
wc/pageturner/profiles/default/metadata.xml
wc/pageturner/profiles/default/propertiestool.xml
wc/pageturner/profiles/default/types.xml
wc/pageturner/profiles/default/types/File.xml
wc/pageturner/profiles/uninstall/import_steps.xml
wc/pageturner/profiles/uninstall/wc.pageturner-uninstall.txt
wc/pageturner/resources/FlexPaperViewer.swf
wc/pageturner/resources/application-pdf.png
wc/pageturner/resources/flexpaper_flash.js
wc/pageturner/resources/playerProductInstall.swf
wc/pageturner/resources/styles.css