Metadata-Version: 1.0
Name: wc.pageturner
Version: 1.3.6
Summary: A Plone product that provides the PDF viewer FlexPaper.
Home-page: https://github.com/collective/wc.pageturner
Author: Nathan Van Gheem
Author-email: vangheem@gmail.com
License: GPL
Keywords: plone pdf flexpaper flex paper scridb
Platform: UNKNOWN
Classifier: Framework :: Plone
Classifier: Programming Language :: Python
